README.rst
setup.py
zkcluster/__init__.py
zkcluster/client.py
zkcluster/cmdline.py
zkcluster/config.py
zkcluster/console.py
zkcluster/exc.py
zkcluster/p2p.py
zkcluster/raft.py
zkcluster/rpc.py
zkcluster/server.py
zkcluster/state.py
zkcluster.egg-info/PKG-INFO
zkcluster.egg-info/SOURCES.txt
zkcluster.egg-info/dependency_links.txt
zkcluster.egg-info/not-zip-safe
zkcluster.egg-info/requires.txt
zkcluster.egg-info/top_level.txt
zkcluster/util/__init__.py
zkcluster/util/async.py
zkcluster/util/compat.py
zkcluster/util/event.py
zkcluster/util/util.py