Metadata-Version: 1.1
Name: zkcluster
Version: 0.0.10
Summary: zzzeek's clustering server framework
Home-page: http://bitbucket.org/zzzeek/zkcluster
Author: Mike Bayer
Author-email: mike@zzzcomputing.com
License: MIT
Platform: UNKNOWN
Classifier: Development Status :: 3 - Alpha
Classifier: Intended Audience :: Developers
Classifier: Programming Language :: Python
Classifier: Programming Language :: Python :: 3
Classifier: Programming Language :: Python :: Implementation :: CPython
Classifier: Programming Language :: Python :: Implementation :: PyPy
